{
  "hash": "c373d823",
  "configHash": "f819982b",
  "lockfileHash": "de1eb8cf",
  "browserHash": "c495c11a",
  "optimized": {
    "react/jsx-dev-runtime": {
      "src": "../../node_modules/react/jsx-dev-runtime.js",
      "file": "react_jsx-dev-runtime.js",
      "fileHash": "d8f60c0c",
      "needsInterop": true
    },
    "react": {
      "src": "../../node_modules/react/index.js",
      "file": "react.js",
      "fileHash": "257d47f4",
      "needsInterop": true
    },
    "@tanstack/react-query": {
      "src": "../../node_modules/@tanstack/react-query/build/modern/index.js",
      "file": "@tanstack_react-query.js",
      "fileHash": "97335c92",
      "needsInterop": false
    },
    "react-router-dom": {
      "src": "../../node_modules/react-router-dom/dist/index.mjs",
      "file": "react-router-dom.js",
      "fileHash": "9caf7853",
      "needsInterop": false
    },
    "react-dom/client": {
      "src": "../../node_modules/react-dom/client.js",
      "file": "react-dom_client.js",
      "fileHash": "141e02dd",
      "needsInterop": true
    }
  },
  "chunks": {
    "chunk-M5IPRDD5": {
      "file": "chunk-M5IPRDD5.js"
    },
    "chunk-TJW4JA7A": {
      "file": "chunk-TJW4JA7A.js"
    }
  }
}